pvgispy/__init__.py
pvgispy/base.py
pvgispy/daily.py
pvgispy/hourly.py
pvgispy/monthly.py
pvgispy/tmy.py
pvgispy-0.1.3.dist-info/LICENSE
pvgispy-0.1.3.dist-info/METADATA
pvgispy-0.1.3.dist-info/WHEEL
pvgispy-0.1.3.dist-info/top_level.txt
pvgispy-0.1.3.dist-info/RECORD
