Metadata-Version: 2.2
Name: pvgispy
Version: 0.1.3
Summary: An inofficial interface for the PVGIS API by the EU Science Hub
Home-page: https://github.com/jannikobenhoff/pvgispy
License: MIT
License-File: LICENSE
Requires-Dist: requests
Dynamic: home-page
Dynamic: license
Dynamic: requires-dist
Dynamic: summary
